odoo/addons/account_spread_cost_revenue/README.rst
odoo/addons/account_spread_cost_revenue/__init__.py
odoo/addons/account_spread_cost_revenue/__manifest__.py
odoo/addons/account_spread_cost_revenue/data/spread_cron.xml
odoo/addons/account_spread_cost_revenue/i18n/account_spread_cost_revenue.pot
odoo/addons/account_spread_cost_revenue/i18n/fr.po
odoo/addons/account_spread_cost_revenue/i18n/nl.po
odoo/addons/account_spread_cost_revenue/i18n/pt.po
odoo/addons/account_spread_cost_revenue/models/__init__.py
odoo/addons/account_spread_cost_revenue/models/account_invoice.py
odoo/addons/account_spread_cost_revenue/models/account_invoice_line.py
odoo/addons/account_spread_cost_revenue/models/account_spread.py
odoo/addons/account_spread_cost_revenue/models/account_spread_line.py
odoo/addons/account_spread_cost_revenue/models/account_spread_template.py
odoo/addons/account_spread_cost_revenue/models/res_company.py
odoo/addons/account_spread_cost_revenue/readme/CONFIGURE.rst
odoo/addons/account_spread_cost_revenue/readme/CONTRIBUTORS.rst
odoo/addons/account_spread_cost_revenue/readme/CREDITS.rst
odoo/addons/account_spread_cost_revenue/readme/DESCRIPTION.rst
odoo/addons/account_spread_cost_revenue/readme/HISTORY.rst
odoo/addons/account_spread_cost_revenue/readme/USAGE.rst
odoo/addons/account_spread_cost_revenue/security/account_spread_security.xml
odoo/addons/account_spread_cost_revenue/security/ir.model.access.csv
odoo/addons/account_spread_cost_revenue/static/description/create_spread.png
odoo/addons/account_spread_cost_revenue/static/description/icon.png
odoo/addons/account_spread_cost_revenue/static/description/index.html
odoo/addons/account_spread_cost_revenue/static/description/invoice_line_1.png
odoo/addons/account_spread_cost_revenue/static/description/invoice_line_2.png
odoo/addons/account_spread_cost_revenue/static/description/spread.png
odoo/addons/account_spread_cost_revenue/static/description/update_spread.png
odoo12_addon_account_spread_cost_revenue-12.0.1.2.1.dist-info/METADATA
odoo12_addon_account_spread_cost_revenue-12.0.1.2.1.dist-info/WHEEL
odoo12_addon_account_spread_cost_revenue-12.0.1.2.1.dist-info/top_level.txt
odoo12_addon_account_spread_cost_revenue-12.0.1.2.1.dist-info/RECORD
